ad_import/VERSION
ad_import/__init__.py
ad_import/admin.py
ad_import/apps.py
ad_import/urls.py
ad_import/views.py
ad_import/ad/__init__.py
ad_import/ad/active_directory.py
ad_import/ad/ad_object.py
ad_import/ad/paginated_lookup.py
ad_import/ad/sid.py
ad_import/load_data/LoadAd.py
ad_import/load_data/LoadUsers.py
ad_import/load_data/__init__.py
ad_import/load_data/load_computer.py
ad_import/load_data/load_servers.py
ad_import/load_data/load_workstations.py
ad_import/management/__init__.py
ad_import/management/commands/ADBaseCommand.py
ad_import/management/commands/__init__.py
ad_import/management/commands/ad_load_servers.py
ad_import/management/commands/ad_load_users.py
ad_import/management/commands/ad_load_workstations.py
ad_import/migrations/0001_initial.py
ad_import/migrations/0002_auto_20200917_2001.py
ad_import/migrations/0003_server_workstation.py
ad_import/migrations/0004_target_choices.py
ad_import/migrations/0005_directory_related_name.py
ad_import/migrations/0006_manager_set_null.py
ad_import/migrations/0007_name_fields.py
ad_import/migrations/0008_sid_bytes.py
ad_import/migrations/0009_user_fields.py
ad_import/migrations/__init__.py
ad_import/models/__init__.py
ad_import/models/computer.py
ad_import/models/directory.py
ad_import/models/query.py
ad_import/models/server.py
ad_import/models/user.py
ad_import/models/workstation.py
ad_import/templates/ad_import/base.html
ad_import/templates/ad_import/computer.html
ad_import/templates/ad_import/user.html
ad_import/utils/__init__.py
ad_import/utils/ad_utils.py
tests/TestSID.py
tests/__init__.py
tests/test_settings.py
django_ad_import-0.9.dist-info/LICENSE
django_ad_import-0.9.dist-info/METADATA
django_ad_import-0.9.dist-info/WHEEL
django_ad_import-0.9.dist-info/top_level.txt
django_ad_import-0.9.dist-info/RECORD
