Metadata-Version: 2.1
Name: django-ad-import
Version: 0.9
Summary: A django app to import information from Active Directory to a database
Home-page: https://github.com/StorFollo-IKT/django-ad-import
Author: Anders Birkenes
Author-email: anders.birkenes@storfolloikt.no
License: GPL
Platform: UNKNOWN
Classifier: Framework :: Django
Classifier: Framework :: Django :: 2.1
Classifier: Intended Audience :: Developers
Classifier: License :: OSI Approved :: GNU General Public License v3 or later (GPLv3+)
Classifier: Operating System :: OS Independent
Classifier: Programming Language :: Python
Classifier: Programming Language :: Python :: 3.7
Classifier: Programming Language :: Python :: 3.8
License-File: LICENSE
Requires-Dist: django (<4,>=2)
